{
    "id": -1,
    "pos": {
        "x": -1,
        "y": -1
    },
    "symbol": 114,
    "color": {
        "r": 68,
        "g": 53,
        "b": 33
    },
    "name": "Rat",
    "hp": 12,
    "vision_radius": 4,
    "inventory": {
        "items": [
            {
                "name": "Dagger",
                "id": -1,
                "category": 0,
                "item": {
                    "physical_dmg": 4,
                    "fire_dmg": 0,
                    "cold_dmg": 0,
                    "lightning_dmg": 0,
                    "accuracy": 92
                },
                "equipped": true
            },
            {
                "name": "Rags",
                "id": -1,
                "category": 1,
                "item": {
                    "defence": 0,
                    "evasion": 20,
                    "physical_resistance": 0,
                    "fire_resistance": 0,
                    "cold_resistance": 5,
                    "lightning_resistance": 0
                },
                "equipped": true
            }
        ]
    },
    "is_alive": true,
    "depth": 1
}